odoo/addons/partner_contact_birthplace/README.rst
odoo/addons/partner_contact_birthplace/__init__.py
odoo/addons/partner_contact_birthplace/__manifest__.py
odoo/addons/partner_contact_birthplace/i18n/ca.po
odoo/addons/partner_contact_birthplace/i18n/es.po
odoo/addons/partner_contact_birthplace/i18n/es_ES.po
odoo/addons/partner_contact_birthplace/i18n/it.po
odoo/addons/partner_contact_birthplace/i18n/partner_contact_birthplace.pot
odoo/addons/partner_contact_birthplace/models/__init__.py
odoo/addons/partner_contact_birthplace/models/res_partner.py
odoo/addons/partner_contact_birthplace/readme/CONTRIBUTORS.md
odoo/addons/partner_contact_birthplace/readme/DESCRIPTION.md
odoo/addons/partner_contact_birthplace/readme/USAGE.md
odoo/addons/partner_contact_birthplace/static/description/icon.png
odoo/addons/partner_contact_birthplace/static/description/index.html
odoo/addons/partner_contact_birthplace/static/description/partner_form.png
odoo/addons/partner_contact_birthplace/views/res_partner.xml
odoo_addon_partner_contact_birthplace-19.0.1.0.0.2.dist-info/METADATA
odoo_addon_partner_contact_birthplace-19.0.1.0.0.2.dist-info/WHEEL
odoo_addon_partner_contact_birthplace-19.0.1.0.0.2.dist-info/top_level.txt
odoo_addon_partner_contact_birthplace-19.0.1.0.0.2.dist-info/RECORD
