Metadata-Version: 2.1
Name: odoo-addon-partner_contact_birthplace
Version: 19.0.1.0.0.2
Requires-Dist: odoo-addon-partner_contact_personal_information_page==19.0.*
Requires-Dist: odoo==19.0.*
Summary: This module allows to define a birthplace for partners.
Home-page: https://github.com/OCA/partner-contact
License: AGPL-3
Author: Agile Business Group,GRAP, Odoo Community Association (OCA)
Author-email: support@odoo-community.org
Classifier: Programming Language :: Python
Classifier: Framework :: Odoo
Classifier: Framework :: Odoo :: 19.0
Classifier: License :: OSI Approved :: GNU Affero General Public License v3
